temporary/__init__.py
temporary/directories.py
temporary/files.py
temporary/util.py
temporary-3.0.0.dist-info/top_level.txt
temporary-3.0.0.dist-info/METADATA
temporary-3.0.0.dist-info/DESCRIPTION.rst
temporary-3.0.0.dist-info/metadata.json
temporary-3.0.0.dist-info/WHEEL
temporary-3.0.0.dist-info/RECORD
